tap_aftership/__init__.py
tap_aftership/client.py
tap_aftership/schemas/tracking.json
tap_aftership/schemas/trackings.json
tap_aftership/streams.py
tap_aftership/tap.py
tap_aftership/tests/__init__.py
tap_aftership/tests/test_core.py
tap_aftership/tests/test_streams.py
tap_aftership-0.0.4.dist-info/entry_points.txt
tap_aftership-0.0.4.dist-info/WHEEL
tap_aftership-0.0.4.dist-info/METADATA
tap_aftership-0.0.4.dist-info/RECORD
