Metadata-Version: 2.1
Name: tap-aftership
Version: 0.0.4
Summary: `tap-aftership` is a Singer tap for AfterShip, built with the Meltano Singer SDK.
License: Apache 2.0
Keywords: ELT,AfterShip
Author: harrystech
Requires-Python: >=3.7.1,<3.11
Classifier: License :: Other/Proprietary License
Classifier: Programming Language :: Python :: 3
Classifier: Programming Language :: Python :: 3.8
Classifier: Programming Language :: Python :: 3.9
Classifier: Programming Language :: Python :: 3.10
Requires-Dist: requests (>=2.25.1,<3.0.0)
Requires-Dist: singer-sdk (>=0.13.0,<0.14.0)
